rutils/__init__.py
rutils/common.py
rutils/time.py
rutils/video.py
rutils-0.4.0.dist-info/LICENSE
rutils-0.4.0.dist-info/METADATA
rutils-0.4.0.dist-info/WHEEL
rutils-0.4.0.dist-info/top_level.txt
rutils-0.4.0.dist-info/RECORD
