Metadata-Version: 2.1
Name: rutils
Version: 0.4.0
Summary: Utils for Computer Vision
Home-page: UNKNOWN
Author: rivergold
Author-email: jinghe.rivergold@gmail.com
License: MIT
Platform: UNKNOWN
License-File: LICENSE
Requires-Dist: pillow
Requires-Dist: pymediainfo
Requires-Dist: rlogger
